python_slippery-1.0.0.dist-info/DESCRIPTION.rst
python_slippery-1.0.0.dist-info/METADATA
python_slippery-1.0.0.dist-info/RECORD
python_slippery-1.0.0.dist-info/WHEEL
python_slippery-1.0.0.dist-info/metadata.json
python_slippery-1.0.0.dist-info/top_level.txt
slippery/__init__.py
slippery/burner_email.py
slippery/parser.py
slippery/proxy.py
slippery/validator.py
