Metadata-Version: 2.0
Name: python-slippery
Version: 1.0.0
Summary: A library for interacting with the slippery.email website
Home-page: https://bitbucket.org/carter-yagemann/python-slippery
Author: Carter Yagemann
Author-email: carter.yagemann@gmail.com
License: GPLv3+
Download-URL: https://bitbucket.org/carter-yagemann/python-slippery
Keywords: slippery api burner email
Platform: Any
Classifier: Development Status :: 5 - Production/Stable
Classifier: Intended Audience :: Developers
Classifier: License :: OSI Approved :: GNU General Public License v3 or later (GPLv3+)
Classifier: Operating System :: OS Independent
Classifier: Topic :: Software Development :: Libraries :: Python Modules
Classifier: Topic :: Communications :: Chat
Classifier: Topic :: Internet
Classifier: Programming Language :: Python
Classifier: Programming Language :: Python :: 2
Classifier: Programming Language :: Python :: 2.7
Requires-Dist: PySocks
Requires-Dist: lxml
